tacotruck/___init__.py
tacotruck/analysis.py
tacotruck/utils.py
tacotruck-0.2.0.dist-info/licenses/LICENSE
tacotruck-0.2.0.dist-info/METADATA
tacotruck-0.2.0.dist-info/WHEEL
tacotruck-0.2.0.dist-info/top_level.txt
tacotruck-0.2.0.dist-info/RECORD
