Metadata-Version: 2.4
Name: tacotruck
Version: 0.2.0
Summary: Battery degradation models from FleetDNA utils
Author-email: Joseph Silberman <jsph.slbrmn@gmail.com>
License: MIT
Classifier: Programming Language :: Python :: 3
Classifier: License :: OSI Approved :: MIT License
Classifier: Operating System :: OS Independent
Requires-Python: <3.13,>=3.9
License-File: LICENSE
Dynamic: license-file
